{"id":15,"name":"Nathanael Senger","address":{"address":"05180 Orie Field","city":"Port Floyd","state":"Texas","zip":"85364"},"reviews":["http://localhost:3000/reviews/53","http://localhost:3000/reviews/54","http://localhost:3000/reviews/55","http://localhost:3000/reviews/56","http://localhost:3000/reviews/57"],"products":["http://localhost:3000/products/931","http://localhost:3000/products/592","http://localhost:3000/products/373","http://localhost:3000/products/270","http://localhost:3000/products/320","http://localhost:3000/products/173","http://localhost:3000/products/781","http://localhost:3000/products/402","http://localhost:3000/products/515","http://localhost:3000/products/240","http://localhost:3000/products/303","http://localhost:3000/products/777","http://localhost:3000/products/593","http://localhost:3000/products/40","http://localhost:3000/products/821","http://localhost:3000/products/406"]}