{"id":226,"name":"Aaliyah Ratke","address":{"address":"00806 Kuhic Shore","city":"New Tedhaven","state":"South Carolina","zip":"65985"},"reviews":["http://localhost:3000/reviews/825"],"products":["http://localhost:3000/products/557","http://localhost:3000/products/642","http://localhost:3000/products/763","http://localhost:3000/products/243","http://localhost:3000/products/427","http://localhost:3000/products/944","http://localhost:3000/products/216","http://localhost:3000/products/980","http://localhost:3000/products/85","http://localhost:3000/products/738"]}